wotwrapper
