Metadata-Version: 1.0
Name: wotwrapper
Version: 0.0.5
Summary: A library to wrap a python object onto the Wotio Operating Enviroment
Home-page: http://github.com/wotio/wotwrapper
Author: Andrew Khoury
Author-email: drew@wot.io
License: MIT
Platform: UNKNOWN
